SPI2Py/__init__.py
SPI2Py/example.py
spi2py-0.0.1.dist-info/METADATA
spi2py-0.0.1.dist-info/WHEEL
spi2py-0.0.1.dist-info/licenses/LICENSE.txt
spi2py-0.0.1.dist-info/RECORD
