Metadata-Version: 2.1
Name: SPI2Py
Version: 0.0.1
Summary: Spatial packaging of interconnected systems with physical interactions
Project-URL: Homepage, https://github.com/pypa/sampleproject
Project-URL: Bug Tracker, https://github.com/pypa/sampleproject/issues
Author-email: Chad Peterson <cp44@illinois.edu>
License-File: LICENSE.txt
Classifier: License :: OSI Approved :: MIT License
Classifier: Operating System :: OS Independent
Classifier: Programming Language :: Python :: 3
Requires-Python: >=3.7
